pyfaulttolerance/__init__.py
pyfaulttolerance/bulkhead.py
pyfaulttolerance/circuit_breaker.py
pyfaulttolerance/exceptions.py
pyfaulttolerance/fallback.py
pyfaulttolerance/retry_async.py
pyfaulttolerance/timeout.py
pyfaulttolerance/timeout_async.py
pyfaulttolerance-0.1.3.dist-info/METADATA
pyfaulttolerance-0.1.3.dist-info/WHEEL
pyfaulttolerance-0.1.3.dist-info/top_level.txt
pyfaulttolerance-0.1.3.dist-info/RECORD
