Metadata-Version: 2.4
Name: pyfaulttolerance
Version: 0.1.3
Summary: Microframework de tolerância a falhas inspirado no SmallRye Fault Tolerance
Author: Fabio Gomes Rocha
License: MIT
Requires-Python: >=3.13
Requires-Dist: coverage>=7.8.0
Requires-Dist: pytest>=8.3.5
Requires-Dist: pytest-asyncio>=0.26.0
